__init__.py
client.py
environment.py
core/__init__.py
core/api_error.py
core/datetime_utils.py
core/jsonable_encoder.py
core/remove_none_from_headers.py
resources/__init__.py
resources/api_keys/__init__.py
resources/api_keys/client.py
resources/api_keys/types/__init__.py
resources/api_keys/types/rotate_timings.py
resources/application_user/__init__.py
resources/application_user/client.py
resources/application_user/types/__init__.py
resources/application_user/types/api_key.py
resources/application_user/types/application.py
resources/application_user/types/application_base_url.py
resources/application_user/types/application_base_url_endpoint.py
resources/application_user/types/application_role.py
resources/application_user/types/application_user.py
resources/application_user/types/application_user_create_response.py
resources/application_user/types/application_version.py
resources/application_user/types/organization.py
resources/logs/__init__.py
resources/logs/client.py
resources/logs/types/__init__.py
resources/logs/types/get_logs_by_application_response.py
resources/logs/types/log.py
resources/parse/__init__.py
resources/parse/client.py
resources/parse/types/__init__.py
resources/parse/types/application_parse_response.py
resources/parse/types/endpoint_pre_process_type.py
resources/parse/types/idempotency_key_type.py
resources/parse/types/post_process_api_response.py
resources/parse/types/pre_process_api_response.py
resources/parse/types/request_pre_process_response.py
resources/parse/types/request_type.py
resources/parse/types/return_back_to_user_error_response.py
resources/parse/types/return_back_to_user_union_type.py
resources/parse/types/user_parse_response.py
resources/tiers/__init__.py
resources/tiers/client.py
resources/tiers/types/__init__.py
resources/tiers/types/application_rate_limit.py
resources/tiers/types/application_tier.py
integral_python_sdk_shreypjain-0.1.0.dist-info/METADATA
integral_python_sdk_shreypjain-0.1.0.dist-info/WHEEL
integral_python_sdk_shreypjain-0.1.0.dist-info/RECORD
